bayes_window/__init__.py
bayes_window/bayes_window.py
bayes_window/cli.py
bayes_window/fitting.py
bayes_window/generative_models.py
bayes_window/model_comparison.py
bayes_window/models.py
bayes_window/utils.py
bayes_window/visualization.py
bayes_window/workflow.py
bayes_window-0.1.1.dist-info/AUTHORS.rst
bayes_window-0.1.1.dist-info/LICENSE
bayes_window-0.1.1.dist-info/METADATA
bayes_window-0.1.1.dist-info/WHEEL
bayes_window-0.1.1.dist-info/entry_points.txt
bayes_window-0.1.1.dist-info/top_level.txt
bayes_window-0.1.1.dist-info/RECORD
