Metadata-Version: 2.1
Name: bayes-window
Version: 0.1.1
Summary: Pretty and easy Bayesian estimation with data overlay
Home-page: https://github.com/mmyros/bayes_window
Author: Maxym Myroshnychenko
Author-email: mmyros@gmail.com
License: MIT license
Keywords: bayes_window
Platform: UNKNOWN
Classifier: Development Status :: 2 - Pre-Alpha
Classifier: Intended Audience :: Developers
Classifier: License :: OSI Approved :: MIT License
Classifier: Natural Language :: English
Classifier: Programming Language :: Python :: 3.7
Classifier: Programming Language :: Python :: 3.8
Requires-Python: >=3.6
